<?xml version="1.0"?>
<?xml-stylesheet type="text/xsl" href="configuration.xsl"?>

<!-- Put site-specific property overrides in this file. -->

<!-- Mode 1 -->
<configuration>
  <property>
    <name>plugin.includes</name>
    <!--<value>protocol-http|urlfilter-regex|parse-(html|tika)|index-(basic|anchor)|indexer-solr|scoring-opic|urlnormalizer-(pass|regex|basic)|extractor</value>-->
    <value>protocol-http|urlfilter-regex|parse-(html)|index-(basic|anchor)|indexer-solr|extractor|scoring-opic|urlnormalizer-(pass|regex|basic)</value>
  </property>
</configuration>

